pose_estimation_recognition_utils/ImageSkeletonData.py
pose_estimation_recognition_utils/ImageSkeletonLoader.py
pose_estimation_recognition_utils/PEImage.py
pose_estimation_recognition_utils/PEVideo.py
pose_estimation_recognition_utils/SAD.py
pose_estimation_recognition_utils/Save2DData.py
pose_estimation_recognition_utils/Save2DDataWithConfidence.py
pose_estimation_recognition_utils/Save2DDataWithName.py
pose_estimation_recognition_utils/Save2DDataWithNameAndConfidence.py
pose_estimation_recognition_utils/SkeletonDataPoint.py
pose_estimation_recognition_utils/SkeletonDataPointWithConfidence.py
pose_estimation_recognition_utils/SkeletonDataPointWithName.py
pose_estimation_recognition_utils/SkeletonDataPointWithNameAndConfidence.py
pose_estimation_recognition_utils/VideoSkeletonData.py
pose_estimation_recognition_utils/VideoSkeletonLoader.py
pose_estimation_recognition_utils/__init__.py
pose_estimation_recognition_utils-0.3.0.dist-info/METADATA
pose_estimation_recognition_utils-0.3.0.dist-info/WHEEL
pose_estimation_recognition_utils-0.3.0.dist-info/top_level.txt
pose_estimation_recognition_utils-0.3.0.dist-info/RECORD
