Metadata-Version: 2.4
Name: pose-estimation-recognition-utils
Version: 0.3.0
Summary: Classes for AI recognition on pose estimation data
Home-page: https://github.com/cobtras/pose-estimation-recognition-utils
Author: Jonas David Stephan, Chanyut Boonkhamsaen, Nathalie Dollmann
Author-email: j.stephan@system-systeme.de
License: Apache 2.0
Requires-Dist: setuptools>=70.0.0
Requires-Dist: numpy>1
Dynamic: author
Dynamic: author-email
Dynamic: description
Dynamic: home-page
Dynamic: license
Dynamic: requires-dist
Dynamic: summary
